azpkg37/__init__.py
azpkg37/azpkg.py
azpkg37/plotting.py
azpkg37-0.1.0.dist-info/LICENSE
azpkg37-0.1.0.dist-info/WHEEL
azpkg37-0.1.0.dist-info/METADATA
azpkg37-0.1.0.dist-info/RECORD
