Metadata-Version: 2.1
Name: azpkg37
Version: 0.1.0
Summary: AZ Testing Package
License: MIT
Author: AraonZ
Requires-Python: >=3.9,<4.0
Classifier: License :: OSI Approved :: MIT License
Classifier: Programming Language :: Python :: 3
Classifier: Programming Language :: Python :: 3.10
Classifier: Programming Language :: Python :: 3.9
Requires-Dist: matplotlib (>=3.5.3,<4.0.0)
